chunjie/__init__.py
chunjie/logo.py
Spring_Festival-2025.1.dist-info/METADATA
Spring_Festival-2025.1.dist-info/WHEEL
Spring_Festival-2025.1.dist-info/top_level.txt
Spring_Festival-2025.1.dist-info/RECORD
