Metadata-Version: 2.1
Name: Spring_Festival
Version: 2025.1
Summary: 2025春节彩蛋
Home-page: https://github.com/QJZX/Spring_Festival
Author: qjzx
